simplePyLogsColor/__init__.py
simplePyLogsColor/simpleLogs.py
simplePyLogsColor-1.1.0.dist-info/LICENSE
simplePyLogsColor-1.1.0.dist-info/METADATA
simplePyLogsColor-1.1.0.dist-info/WHEEL
simplePyLogsColor-1.1.0.dist-info/top_level.txt
simplePyLogsColor-1.1.0.dist-info/RECORD
