Metadata-Version: 2.1
Name: simplePyLogsColor
Version: 1.1.0
Summary: Librería personalizada para logging con colores, con informacion de fecha - hora de ejecución y linea ejecutable (opcional)
Home-page: https://github.com/Pabl0VC/simpleLogs
Author: Pablo Vega C
Author-email: pablovegac.93@gmail.com
License: UNKNOWN
Platform: UNKNOWN
Classifier: Programming Language :: Python :: 3
Classifier: License :: OSI Approved :: MIT License
Classifier: Operating System :: OS Independent
Requires-Python: >=3.6
License-File: LICENSE
Requires-Dist: colorama
